instancemethod/__init__.py
instancemethod-1.5.0.dist-info/METADATA
instancemethod-1.5.0.dist-info/WHEEL
instancemethod-1.5.0.dist-info/licenses/LICENSE
instancemethod-1.5.0.dist-info/RECORD
