Metadata-Version: 2.1
Name: instancemethod
Version: 1.5.0
Summary: Restrict method calls to instances of the owner class.
Project-URL: Homepage, https://github.com/Braden2n/InstanceMethod
Project-URL: Documentation, https://github.com/Braden2n/InstanceMethod
Project-URL: Issues, https://github.com/Braden2n/InstanceMethod/issues
Project-URL: Repository, https://github.com
Project-URL: Changelog, https://github.com/Braden2n/InstanceMethod/activity
Author-email: Braden Toone <braden@toonetown.com>
Maintainer-email: Braden Toone <braden@toonetown.com>
License: MIT License
License-File: LICENSE
Keywords: call,class,instance,method,restrict
Classifier: Development Status :: 5 - Production/Stable
Classifier: Intended Audience :: Developers
Classifier: License :: OSI Approved :: MIT License
Classifier: Natural Language :: English
Classifier: Operating System :: OS Independent
Classifier: Programming Language :: Python :: 3.5
Classifier: Topic :: Software Development :: Libraries :: Python Modules
Requires-Python: >=3.5
